<!DOCTYPE Board_Memory_Definition_File>
<Root name="Philips LPC2146" >
  <MemorySegment size="0x2000" access="ReadOnly" start="0x00000000" name="FLASH" />
  <MemorySegment size="0x7f00" access="Read/Write" start="0x40000000" name="SRAM" />
  <MemorySegment size="0x20000000" access="Read/Write" start="0xE0000000" name="Peripherals" >
    <RegisterGroup start="0xE0000000" name="Watchdog Timer Registers" >
      <Register size="0x4" start="0xE0000000" name="WDMOD" >
        <BitField size="1" start="0" name="WDEN" />
        <BitField size="1" start="1" name="WDRESET" />
        <BitField size="1" start="2" name="WDTOF" />
        <BitField size="1" start="3" name="WDINT" />
      </Register>
      <Register size="0x4" start="0xE0000004" name="WDTC" />
      <Register size="0x4" start="0xE0000008" name="WDFEED" />
      <Register size="0x4" start="0xE000000C" name="WDTV" />
    </RegisterGroup>
    <RegisterGroup start="0xE0004000" name="Timer0 Registers" >
      <Register size="0x4" start="0xE0004000" name="T0IR" >
        <BitField size="1" start="0" name="MR0" />
        <BitField size="1" start="1" name="MR1" />
        <BitField size="1" start="2" name="MR2" />
        <BitField size="1" start="3" name="MR3" />
        <BitField size="1" start="4" name="CR0" />
        <BitField size="1" start="5" name="CR1" />
        <BitField size="1" start="6" name="CR2" />
        <BitField size="1" start="7" name="CR3" />
      </Register>
      <Register size="0x4" start="0xE0004004" name="T0TCR" >
        <BitField size="1" start="0" name="Counter_Enable" />
        <BitField size="1" start="1" name="Counter_Reset" />
      </Register>
      <Register size="0x4" start="0xE0004008" name="T0TC" />
      <Register size="0x4" start="0xE000400C" name="T0PR" />
      <Register size="0x4" start="0xE0004010" name="T0PC" />
      <Register size="0x4" start="0xE0004014" name="T0MCR" >
        <BitField size="1" start="0" name="Interrupt_on_MR0" />
        <BitField size="1" start="1" name="Reset_on_MR0" />
        <BitField size="1" start="2" name="Stop_on_MR0" />
        <BitField size="1" start="3" name="Interrupt_on_MR1" />
        <BitField size="1" start="4" name="Reset_on_MR1" />
        <BitField size="1" start="5" name="Stop_on_MR1" />
        <BitField size="1" start="7" name="Interrupt_on_MR2" />
        <BitField size="1" start="7" name="Reset_on_MR2" />
        <BitField size="1" start="8" name="Stop_on_MR2" />
        <BitField size="1" start="9" name="Interrupt_on_MR3" />
        <BitField size="1" start="10" name="Reset_on_MR3" />
        <BitField size="1" start="11" name="Stop_on_MR3" />
      </Register>
      <Register size="0x4" start="0xE0004018" name="T0MR0" />
      <Register size="0x4" start="0xE000401C" name="T0MR1" />
      <Register size="0x4" start="0xE0004020" name="T0MR2" />
      <Register size="0x4" start="0xE0004024" name="T0MR3" />
      <Register size="0x4" start="0xE0004028" name="T0CCR" >
        <BitField size="1" start="0" name="Capture_on_CAPn_0_rising_edge" />
        <BitField size="1" start="1" name="Capture_on_CAPn_0_falling_edge" />
        <BitField size="1" start="2" name="Interrupt_on_CAPn_0_event" />
        <BitField size="1" start="3" name="Capture_on_CAPn_1_rising_edge" />
        <BitField size="1" start="4" name="Capture_on_CAPn_1_falling_edge" />
        <BitField size="1" start="5" name="Interrupt_on_CAPn_1_event" />
        <BitField size="1" start="7" name="Capture_on_CAPn_2_rising_edge" />
        <BitField size="1" start="7" name="Capture_on_CAPn_2_falling_edge" />
        <BitField size="1" start="8" name="Interrupt_on_CAPn_2_event" />
        <BitField size="1" start="9" name="Capture_on_CAPn_3_rising_edge" />
        <BitField size="1" start="10" name="Capture_on_CAPn_3_falling_edge" />
        <BitField size="1" start="11" name="Interrupt_on_CAPn_3_event" />
      </Register>
      <Register size="0x4" start="0xE000402C" name="T0CR0" />
      <Register size="0x4" start="0xE0004030" name="T0CR1" />
      <Register size="0x4" start="0xE0004034" name="T0CR2" />
      <Register size="0x4" start="0xE0004038" name="T0CR3" />
      <Register size="0x4" start="0xE000403C" name="T0EMR" >
        <BitField size="1" start="0" name="External_Match_0" />
        <BitField size="1" start="1" name="External_Match_1" />
        <BitField size="1" start="2" name="External_Match_2" />
        <BitField size="1" start="3" name="External_Match_3" />
        <BitField size="2" start="4" name="External_Match_Control_0" />
        <BitField size="2" start="6" name="External_Match_Control_1" />
        <BitField size="2" start="8" name="External_Match_Control_2" />
        <BitField size="2" start="10" name="External_Match_Control_3" />
      </Register>
      <Register size="0x4" start="0xE0004070" name="T0CTCR" >
        <BitField size="2" start="0" name="Mode" />
        <BitField size="2" start="2" name="Input_Select" />
      </Register>
    </RegisterGroup>
    <RegisterGroup start="0xE0008000" name="Timer1 Registers" >
      <Register size="0x4" start="0xE0008000" name="T1IR" >
        <BitField size="1" start="0" name="MR0" />
        <BitField size="1" start="1" name="MR1" />
        <BitField size="1" start="2" name="MR2" />
        <BitField size="1" start="3" name="MR3" />
        <BitField size="1" start="4" name="CR0" />
        <BitField size="1" start="5" name="CR1" />
        <BitField size="1" start="6" name="CR2" />
        <BitField size="1" start="7" name="CR3" />
      </Register>
      <Register size="0x4" start="0xE0008004" name="T1TCR" >
        <BitField size="1" start="0" name="Counter_Enable" />
        <BitField size="1" start="1" name="Counter_Reset" />
      </Register>
      <Register size="0x4" start="0xE0008008" name="T1TC" />
      <Register size="0x4" start="0xE000800C" name="T1PR" />
      <Register size="0x4" start="0xE0008010" name="T1PC" />
      <Register size="0x4" start="0xE0008014" name="T1MCR" >
        <BitField size="1" start="0" name="Interrupt_on_MR0" />
        <BitField size="1" start="1" name="Reset_on_MR0" />
        <BitField size="1" start="2" name="Stop_on_MR0" />
        <BitField size="1" start="3" name="Interrupt_on_MR1" />
        <BitField size="1" start="4" name="Reset_on_MR1" />
        <BitField size="1" start="5" name="Stop_on_MR1" />
        <BitField size="1" start="7" name="Interrupt_on_MR2" />
        <BitField size="1" start="7" name="Reset_on_MR2" />
        <BitField size="1" start="8" name="Stop_on_MR2" />
        <BitField size="1" start="9" name="Interrupt_on_MR3" />
        <BitField size="1" start="10" name="Reset_on_MR3" />
        <BitField size="1" start="11" name="Stop_on_MR3" />
      </Register>
      <Register size="0x4" start="0xE0008018" name="T1MR0" />
      <Register size="0x4" start="0xE000801C" name="T1MR1" />
      <Register size="0x4" start="0xE0008020" name="T1MR2" />
      <Register size="0x4" start="0xE0008024" name="T1MR3" />
      <Register size="0x4" start="0xE0008028" name="T1CCR" >
        <BitField size="1" start="0" name="Capture_on_CAPn_0_rising_edge" />
        <BitField size="1" start="1" name="Capture_on_CAPn_0_falling_edge" />
        <BitField size="1" start="2" name="Interrupt_on_CAPn_0_event" />
        <BitField size="1" start="3" name="Capture_on_CAPn_1_rising_edge" />
        <BitField size="1" start="4" name="Capture_on_CAPn_1_falling_edge" />
        <BitField size="1" start="5" name="Interrupt_on_CAPn_1_event" />
        <BitField size="1" start="7" name="Capture_on_CAPn_2_rising_edge" />
        <BitField size="1" start="7" name="Capture_on_CAPn_2_falling_edge" />
        <BitField size="1" start="8" name="Interrupt_on_CAPn_2_event" />
        <BitField size="1" start="9" name="Capture_on_CAPn_3_rising_edge" />
        <BitField size="1" start="10" name="Capture_on_CAPn_3_falling_edge" />
        <BitField size="1" start="11" name="Interrupt_on_CAPn_3_event" />
      </Register>
      <Register size="0x4" start="0xE000802C" name="T1CR0" />
      <Register size="0x4" start="0xE0008030" name="T1CR1" />
      <Register size="0x4" start="0xE0008034" name="T1CR2" />
      <Register size="0x4" start="0xE0008038" name="T1CR3" />
      <Register size="0x4" start="0xE000803C" name="T1EMR" >
        <BitField size="1" start="0" name="External_Match_0" />
        <BitField size="1" start="1" name="External_Match_1" />
        <BitField size="1" start="2" name="External_Match_2" />
        <BitField size="1" start="3" name="External_Match_3" />
        <BitField size="2" start="4" name="External_Match_Control_0" />
        <BitField size="2" start="6" name="External_Match_Control_1" />
        <BitField size="2" start="8" name="External_Match_Control_2" />
        <BitField size="2" start="10" name="External_Match_Control_3" />
      </Register>
      <Register size="0x4" start="0xE0008070" name="T1CTCR" >
        <BitField size="2" start="0" name="Mode" />
        <BitField size="2" start="2" name="Input_Select" />
      </Register>
    </RegisterGroup>
    <RegisterGroup start="0xE000C000" name="UART0 Registers" >
      <Register size="0x1" access="None" start="0xE000C000" name="U0THR" />
      <Register size="0x1" access="None" start="0xE000C000" name="U0DLL" />
      <Register size="0x1" access="None" start="0xE000C000" name="U0RBR" />
      <Register size="0x1" access="None" start="0xE000C004" name="U0DLM" />
      <Register size="0x1" start="0xE000C004" name="U0IER" >
        <BitField size="1" start="0" name="RBR_Interrupt_Enable" />
        <BitField size="1" start="1" name="THRE_Interrupt_Enable" />
        <BitField size="1" start="2" name="Rx_Line_Status_Interrupt_Enable" />
      </Register>
      <Register size="0x1" start="0xE000C008" name="U0IIR" >
        <BitField size="1" start="0" name="Interrupt_Pending" />
        <BitField size="3" start="1" name="Interrupt_Identification" />
        <BitField size="2" start="6" name="FIFO_Enable" />
      </Register>
      <Register size="0x1" access="None" start="0xE000C008" name="U0FCR" >
        <BitField size="1" start="0" name="FIFO_Enable" />
        <BitField size="1" start="1" name="Rx_FIFO_Reset" />
        <BitField size="1" start="2" name="Tx_FIFO_Reset" />
        <BitField size="2" start="6" name="Rx_Trigger_Level_Select" />
      </Register>
      <Register size="0x1" start="0xE000C00C" name="U0LCR" >
        <BitField size="2" start="0" name="Word_Length_Select" />
        <BitField size="1" start="2" name="Stop_Bit_Select" />
        <BitField size="1" start="3" name="Parity_Enable" />
        <BitField size="2" start="4" name="Parity_Select" />
        <BitField size="1" start="6" name="Break_Control" />
        <BitField size="1" start="7" name="Divisor_Latch_Access_Bit" />
      </Register>
      <Register size="0x1" start="0xE000C014" name="U0LSR" >
        <BitField size="1" start="0" name="RDR" />
        <BitField size="1" start="1" name="OE" />
        <BitField size="1" start="2" name="PE" />
        <BitField size="1" start="3" name="FE" />
        <BitField size="1" start="4" name="BI" />
        <BitField size="1" start="5" name="THRE" />
        <BitField size="1" start="6" name="TEMT" />
        <BitField size="1" start="7" name="RXFE" />
      </Register>
      <Register size="0x1" start="0xE000C01C" name="U0SCR" />
    </RegisterGroup>
    <RegisterGroup start="0xE0010000" name="UART1 Registers" >
      <Register size="0x1" access="None" start="0xE0010000" name="U1DLL" />
      <Register size="0x1" access="None" start="0xE0010000" name="U1RBR" />
      <Register size="0x1" access="None" start="0xE0010000" name="U1THR" />
      <Register size="0x1" access="None" start="0xE0010004" name="U1DLM" />
      <Register size="0x1" start="0xE0010004" name="U1IER" >
        <BitField size="1" start="0" name="RBR_Interrupt_Enable" />
        <BitField size="1" start="1" name="THRE_Interrupt_Enable" />
        <BitField size="1" start="2" name="Rx_Line_Status_Interrupt_Enable" />
        <BitField size="1" start="2" name="Modem_Status_Interrupt_Enable" />
      </Register>
      <Register size="0x1" start="0xE0010008" name="U1IIR" >
        <BitField size="1" start="0" name="Interrupt_Pending" />
        <BitField size="3" start="1" name="Interrupt_Identification" />
        <BitField size="2" start="6" name="FIFO_Enable" />
      </Register>
      <Register size="0x1" access="None" start="0xE0010008" name="U1FCR" >
        <BitField size="1" start="0" name="FIFO_Enable" />
        <BitField size="1" start="1" name="Rx_FIFO_Reset" />
        <BitField size="1" start="2" name="Tx_FIFO_Reset" />
        <BitField size="2" start="6" name="Rx_Trigger_Level_Select" />
      </Register>
      <Register size="0x1" start="0xE001000C" name="U1LCR" >
        <BitField size="2" start="0" name="Word_Length_Select" />
        <BitField size="1" start="2" name="Stop_Bit_Select" />
        <BitField size="1" start="3" name="Parity_Enable" />
        <BitField size="2" start="4" name="Parity_Select" />
        <BitField size="1" start="6" name="Break_Control" />
        <BitField size="1" start="7" name="Divisor_Latch_Access_Bit" />
      </Register>
      <Register size="0x1" start="0xE0010010" name="U1MCR" >
        <BitField size="1" start="0" name="DTR_Control" />
        <BitField size="1" start="1" name="RTS_Control" />
        <BitField size="1" start="4" name="Loopback_Mode_Select" />
      </Register>
      <Register size="0x1" start="0xE0010014" name="U1LSR" >
        <BitField size="1" start="0" name="RDR" />
        <BitField size="1" start="1" name="OE" />
        <BitField size="1" start="2" name="PE" />
        <BitField size="1" start="3" name="FE" />
        <BitField size="1" start="4" name="BI" />
        <BitField size="1" start="5" name="THRE" />
        <BitField size="1" start="6" name="TEMT" />
        <BitField size="1" start="7" name="RXFE" />
      </Register>
      <Register size="0x1" start="0xE0010018" name="U1MSR" >
        <BitField size="1" start="0" name="Delta_CTS" />
        <BitField size="1" start="1" name="Delta_DSR" />
        <BitField size="1" start="2" name="Trailing_Edge_RI" />
        <BitField size="1" start="3" name="Delta_DCD" />
        <BitField size="1" start="4" name="CTS" />
        <BitField size="1" start="5" name="DSR" />
        <BitField size="1" start="6" name="RI" />
        <BitField size="1" start="7" name="DCD" />
      </Register>
      <Register size="0x1" start="0xE001001C" name="U1SCR" />
    </RegisterGroup>
    <RegisterGroup start="0xE0014000" name="Pulse Width Modulator Registers" >
      <Register size="0x4" start="0xE0014000" name="PWMIR" >
        <BitField size="1" start="0" name="PWMMR0_Interrupt" />
        <BitField size="1" start="1" name="PWMMR1_Interrupt" />
        <BitField size="1" start="2" name="PWMMR2_Interrupt" />
        <BitField size="1" start="3" name="PWMMR3_Interrupt" />
        <BitField size="1" start="4" name="PWMMR4_Interrupt" />
        <BitField size="1" start="5" name="PWMMR5_Interrupt" />
        <BitField size="1" start="6" name="PWMMR6_Interrupt" />
      </Register>
      <Register size="0x4" start="0xE0014004" name="PWMTCR" >
        <BitField size="1" start="0" name="Counter_Enable" />
        <BitField size="1" start="1" name="Counter_Reset" />
        <BitField size="1" start="3" name="PWM_Enable" />
      </Register>
      <Register size="0x4" start="0xE0014008" name="PWMTC" />
      <Register size="0x4" start="0xE001400C" name="PWMPR" />
      <Register size="0x4" start="0xE0014010" name="PWMPC" />
      <Register size="0x4" start="0xE0014014" name="PWMMCR" >
        <BitField size="1" start="0" name="Interrupt_on_PWMMR0" />
        <BitField size="1" start="0" name="Reset_on_PWMMR0" />
        <BitField size="1" start="0" name="Stop_on_PWMMR0" />
        <BitField size="1" start="0" name="Interrupt_on_PWMMR1" />
        <BitField size="1" start="0" name="Reset_on_PWMMR1" />
        <BitField size="1" start="0" name="Stop_on_PWMMR1" />
        <BitField size="1" start="0" name="Interrupt_on_PWMMR2" />
        <BitField size="1" start="0" name="Reset_on_PWMMR2" />
        <BitField size="1" start="0" name="Stop_on_PWMMR2" />
        <BitField size="1" start="0" name="Interrupt_on_PWMMR3" />
        <BitField size="1" start="0" name="Reset_on_PWMMR3" />
        <BitField size="1" start="0" name="Stop_on_PWMMR3" />
        <BitField size="1" start="0" name="Interrupt_on_PWMMR4" />
        <BitField size="1" start="0" name="Reset_on_PWMMR4" />
        <BitField size="1" start="0" name="Stop_on_PWMMR4" />
        <BitField size="1" start="0" name="Interrupt_on_PWMMR5" />
        <BitField size="1" start="0" name="Reset_on_PWMMR5" />
        <BitField size="1" start="0" name="Stop_on_PWMMR5" />
        <BitField size="1" start="0" name="Interrupt_on_PWMMR6" />
        <BitField size="1" start="0" name="Reset_on_PWMMR6" />
        <BitField size="1" start="0" name="Stop_on_PWMMR6" />
      </Register>
      <Register size="0x4" start="0xE0014018" name="PWMMR0" />
      <Register size="0x4" start="0xE001401C" name="PWMMR1" />
      <Register size="0x4" start="0xE0014020" name="PWMMR2" />
      <Register size="0x4" start="0xE0014024" name="PWMMR3" />
      <Register size="0x4" start="0xE0014040" name="PWMMR4" />
      <Register size="0x4" start="0xE0014044" name="PWMMR5" />
      <Register size="0x4" start="0xE0014048" name="PWMMR6" />
      <Register size="0x4" start="0xE001404C" name="PWMPCR" >
        <BitField size="1" start="2" name="PWMSEL2" />
        <BitField size="1" start="3" name="PWMSEL3" />
        <BitField size="1" start="4" name="PWMSEL4" />
        <BitField size="1" start="5" name="PWMSEL5" />
        <BitField size="1" start="6" name="PWMSEL6" />
        <BitField size="1" start="9" name="PWMENA1" />
        <BitField size="1" start="10" name="PWMENA2" />
        <BitField size="1" start="11" name="PWMENA3" />
        <BitField size="1" start="12" name="PWMENA4" />
        <BitField size="1" start="13" name="PWMENA5" />
        <BitField size="1" start="14" name="PWMENA6" />
      </Register>
      <Register size="0x4" start="0xE0014050" name="PWMLER" >
        <BitField size="1" start="0" name="Enable_PWM_Match_0_Latch" />
        <BitField size="1" start="1" name="Enable_PWM_Match_1_Latch" />
        <BitField size="1" start="2" name="Enable_PWM_Match_2_Latch" />
        <BitField size="1" start="3" name="Enable_PWM_Match_3_Latch" />
        <BitField size="1" start="4" name="Enable_PWM_Match_4_Latch" />
        <BitField size="1" start="5" name="Enable_PWM_Match_5_Latch" />
        <BitField size="1" start="6" name="Enable_PWM_Match_6_Latch" />
      </Register>
    </RegisterGroup>
    <RegisterGroup start="0xE001C000" name="I2C0 Registers" >
      <Register size="0x1" start="0xE001C000" name="I2C0CONSET" >
        <BitField size="1" start="2" name="AA" />
        <BitField size="1" start="3" name="SI" />
        <BitField size="1" start="4" name="STO" />
        <BitField size="1" start="5" name="STA" />
        <BitField size="1" start="6" name="I2EN" />
      </Register>
      <Register size="0x1" start="0xE001C004" name="I2C0STAT" />
      <Register size="0x1" start="0xE001C008" name="I2C0DAT" />
      <Register size="0x1" start="0xE001C00C" name="I2C0ADR" >
        <BitField size="1" start="0" name="GC" />
        <BitField size="6" start="1" name="Address" />
      </Register>
      <Register size="0x2" start="0xE001C010" name="I2C0SCLH" />
      <Register size="0x2" start="0xE001C014" name="I2C0SCLL" />
      <Register size="0x1" start="0xE001C018" name="I2C0CONCLR" >
        <BitField size="1" start="2" name="AAC" />
        <BitField size="1" start="3" name="SIC" />
        <BitField size="1" start="5" name="STAC" />
        <BitField size="1" start="6" name="I2ENC" />
      </Register>
    </RegisterGroup>
    <RegisterGroup start="0xE0020000" name="SPI Registers" >
      <Register size="0x1" start="0xE0020000" name="SPCR" >
        <BitField size="1" start="3" name="CPHA" />
        <BitField size="1" start="4" name="CPOL" />
        <BitField size="1" start="5" name="MSTR" />
        <BitField size="1" start="6" name="LSBF" />
        <BitField size="1" start="7" name="SPIE" />
      </Register>
      <Register size="0x1" start="0xE0020004" name="SPSR" >
        <BitField size="1" start="3" name="ABRT" />
        <BitField size="1" start="4" name="MODF" />
        <BitField size="1" start="5" name="ROVR" />
        <BitField size="1" start="6" name="WCOL" />
        <BitField size="1" start="7" name="SPIF" />
      </Register>
      <Register size="0x1" start="0xE0020008" name="SPDR" />
      <Register size="0x1" start="0xE002000C" name="SPCCR" />
      <Register size="0x1" start="0xE002001C" name="SPINT" />
    </RegisterGroup>
    <RegisterGroup start="0xE0024000" name="Real Time Clock Registers" >
      <Register size="0x4" start="0xE0024000" name="ILR" >
        <BitField size="1" start="0" name="RTCCIF" />
        <BitField size="1" start="1" name="RTCALF" />
      </Register>
      <Register size="0x4" start="0xE0024004" name="CTC" >
        <BitField size="15" start="1" name="Clock_Tick_Counter" />
      </Register>
      <Register size="0x4" start="0xE0024008" name="CCR" >
        <BitField size="1" start="0" name="CLKEN" />
        <BitField size="1" start="1" name="CTCRST" />
        <BitField size="2" start="2" name="CTTEST" />
      </Register>
      <Register size="0x4" start="0xE002400C" name="CIIR" />
      <Register size="0x4" start="0xE0024010" name="AMR" >
        <BitField size="1" start="0" name="AMRSEC" />
        <BitField size="1" start="1" name="AMRMIN" />
        <BitField size="1" start="2" name="AMRHOUR" />
        <BitField size="1" start="3" name="AMRDOM" />
        <BitField size="1" start="4" name="AMRDOW" />
        <BitField size="1" start="5" name="AMRDOY" />
        <BitField size="1" start="6" name="AMRMON" />
        <BitField size="1" start="7" name="AMRYEAR" />
      </Register>
      <Register size="0x4" start="0xE0024014" name="CTIME0" >
        <BitField size="6" start="0" name="Seconds" />
        <BitField size="6" start="8" name="Minutes" />
        <BitField size="5" start="16" name="Hours" />
        <BitField size="5" start="27" name="Day_of_Week" />
      </Register>
      <Register size="0x4" start="0xE0024018" name="CTIME1" >
        <BitField size="5" start="0" name="Day_of_Month" />
        <BitField size="4" start="8" name="Month" />
        <BitField size="12" start="16" name="Year" />
      </Register>
      <Register size="0x4" start="0xE002401C" name="CTIME2" >
        <BitField size="12" start="0" name="Day_of_Year" />
      </Register>
      <Register size="0x4" start="0xE0024020" name="SEC" />
      <Register size="0x4" start="0xE0024024" name="MIN" />
      <Register size="0x4" start="0xE0024028" name="HOUR" />
      <Register size="0x4" start="0xE002402C" name="DOM" />
      <Register size="0x4" start="0xE0024030" name="DOW" />
      <Register size="0x4" start="0xE0024034" name="DOY" />
      <Register size="0x4" start="0xE0024038" name="MONTH" />
      <Register size="0x4" start="0xE002403C" name="YEAR" />
      <Register size="0x4" start="0xE0024060" name="ALSEC" />
      <Register size="0x4" start="0xE0024064" name="ALMIN" />
      <Register size="0x4" start="0xE0024068" name="ALHOUR" />
      <Register size="0x4" start="0xE002406C" name="ALDOM" />
      <Register size="0x4" start="0xE0024070" name="ALDOW" />
      <Register size="0x4" start="0xE0024074" name="ALDOY" />
      <Register size="0x4" start="0xE0024078" name="ALMON" />
      <Register size="0x4" start="0xE002407C" name="ALYEAR" />
      <Register size="0x4" start="0xE0024080" name="PREINT" />
      <Register size="0x4" start="0xE0024084" name="PREFRAC" />
    </RegisterGroup>
    <RegisterGroup start="0xE0028000" name="GPIO Registers" >
      <Register size="0x4" start="0xE0028000" name="IO0PIN" />
      <Register size="0x4" start="0xE0028004" name="IO0SET" />
      <Register size="0x4" start="0xE0028008" name="IO0DIR" />
      <Register size="0x4" start="0xE002800C" name="IO0CLR" />
      <Register size="0x4" start="0xE0028010" name="IO1PIN" />
      <Register size="0x4" start="0xE0028014" name="IO1SET" />
      <Register size="0x4" start="0xE0028018" name="IO1DIR" />
      <Register size="0x4" start="0xE002801C" name="IO1CLR" />
    </RegisterGroup>
    <RegisterGroup start="0xE002C000" name="Pin Connect Block Registers" >
      <Register size="0x4" start="0xE002C000" name="PINSEL0" />
      <Register size="0x4" start="0xE002C004" name="PINSEL1" />
      <Register size="0x4" start="0xE002C014" name="PINSEL2" />
    </RegisterGroup>
    <RegisterGroup start="0xE0034000" name="AD0" >
      <Register size="0x4" start="0xE0034000" name="AD0CR" >
        <BitField size="8" start="0" name="SEL" />
        <BitField size="8" start="8" name="CLKDIV" />
        <BitField size="1" start="16" name="BURST" />
        <BitField size="3" start="17" name="CLKS" />
        <BitField size="1" start="21" name="PDN" />
        <BitField size="2" start="22" name="TEST1_0" />
        <BitField size="3" start="24" name="START" />
        <BitField size="1" start="27" name="EDGE" />
      </Register>
      <Register size="0x4" start="0xE0034004" name="AD0DR" >
        <BitField size="10" start="6" name="VddA" />
        <BitField size="3" start="24" name="CHN" />
        <BitField size="1" start="30" name="OVERUN" />
        <BitField size="1" start="31" name="DONE" />
      </Register>
      <Register size="0x4" start="0xE0034008" name="ADGSR" >
        <BitField size="1" start="16" name="BURST" />
        <BitField size="3" start="24" name="START" />
        <BitField size="1" start="27" name="EDGE" />
      </Register>
    </RegisterGroup>
    <RegisterGroup start="0xE005C000" name="I2C1 Registers" >
      <Register size="0x1" start="0xE005C000" name="I2C1CONSET" >
        <BitField size="1" start="2" name="AA" />
        <BitField size="1" start="3" name="SI" />
        <BitField size="1" start="4" name="STO" />
        <BitField size="1" start="5" name="STA" />
        <BitField size="1" start="6" name="I2EN" />
      </Register>
      <Register size="0x1" start="0xE005C004" name="I2C1STAT" />
      <Register size="0x1" start="0xE005C008" name="I2C1DAT" />
      <Register size="0x1" start="0xE005C00C" name="I2C1ADR" >
        <BitField size="1" start="0" name="GC" />
        <BitField size="6" start="1" name="Address" />
      </Register>
      <Register size="0x2" start="0xE005C010" name="I2C1SCLH" />
      <Register size="0x2" start="0xE005C014" name="I2C1SCLL" />
      <Register size="0x1" start="0xE005C018" name="I2C1CONCLR" >
        <BitField size="1" start="2" name="AAC" />
        <BitField size="1" start="3" name="SIC" />
        <BitField size="1" start="5" name="STAC" />
        <BitField size="1" start="6" name="I2ENC" />
      </Register>
    </RegisterGroup>
    <RegisterGroup start="0xE0060000" name="AD1" >
      <Register size="0x4" start="0xE0060000" name="AD1CR" >
        <BitField size="8" start="0" name="SEL" />
        <BitField size="8" start="8" name="CLKDIV" />
        <BitField size="1" start="16" name="BURST" />
        <BitField size="3" start="17" name="CLKS" />
        <BitField size="1" start="21" name="PDN" />
        <BitField size="2" start="22" name="TEST1_0" />
        <BitField size="3" start="24" name="START" />
        <BitField size="1" start="27" name="EDGE" />
      </Register>
      <Register size="0x4" start="0xE0060004" name="AD1DR" >
        <BitField size="10" start="6" name="VddA" />
        <BitField size="3" start="24" name="CHN" />
        <BitField size="1" start="30" name="OVERUN" />
        <BitField size="1" start="31" name="DONE" />
      </Register>
    </RegisterGroup>
    <RegisterGroup start="0xE0068000" name="SSP" >
      <Register size="0x4" start="0xE0068000" name="SSPCR0" >
        <BitField size="4" start="0" name="DSS" />
        <BitField size="2" start="4" name="FRF" />
        <BitField size="1" start="6" name="SPO" />
        <BitField size="1" start="7" name="SPH" />
        <BitField size="8" start="8" name="SCR" />
      </Register>
      <Register size="0x4" start="0xE0068004" name="SSPCR1" >
        <BitField size="1" start="0" name="LBE" />
        <BitField size="1" start="1" name="SSE" />
        <BitField size="1" start="2" name="MS" />
        <BitField size="1" start="3" name="SOD" />
      </Register>
      <Register size="0x4" start="0xE0068008" name="SSPDR" />
      <Register size="0x4" start="0xE006800C" name="SSPSR" >
        <BitField size="1" start="0" name="TFE" />
        <BitField size="1" start="1" name="TNF" />
        <BitField size="1" start="2" name="RNE" />
        <BitField size="1" start="3" name="RFF" />
        <BitField size="1" start="4" name="BSY" />
      </Register>
      <Register size="0x4" start="0xE0068010" name="SSPCPSR" />
      <Register size="0x4" start="0xE0068014" name="SSPIMSC" >
        <BitField size="1" start="0" name="RORIM" />
        <BitField size="1" start="1" name="RTIM" />
        <BitField size="1" start="2" name="RXIM" />
        <BitField size="1" start="3" name="TXIM" />
      </Register>
      <Register size="0x4" start="0xE0068018" name="SSPRIS" >
        <BitField size="1" start="0" name="RORRIS" />
        <BitField size="1" start="1" name="RTRIS" />
        <BitField size="1" start="2" name="RXRIS" />
        <BitField size="1" start="3" name="TXRIS" />
      </Register>
      <Register size="0x4" start="0xE006801C" name="SSPMIS" >
        <BitField size="1" start="0" name="RORMIS" />
        <BitField size="1" start="1" name="RTMIS" />
        <BitField size="1" start="2" name="RXMIS" />
        <BitField size="1" start="3" name="TXMIS" />
      </Register>
      <Register size="0x4" start="0xE0068020" name="SSPICR" >
        <BitField size="1" start="0" name="RORIC" />
        <BitField size="1" start="1" name="RTIC" />
      </Register>
      <Register size="0x4" start="0xE0068FE0" name="SSPPeriphID0_3" />
      <Register size="0x4" start="0xE0068FFC" name="SSPPCellID0_3" />
    </RegisterGroup>
    <RegisterGroup start="0xE006C000" name="DA" >
      <Register size="0x4" start="0xE006C000" name="DACR" >
        <BitField size="10" start="6" name="VALUE" />
        <BitField size="1" start="16" name="BIAS" />
      </Register>
    </RegisterGroup>
    <RegisterGroup start="0xE01FC000" name="System Control Block" >
      <Register size="0x1" start="0xE01FC000" name="MAMCR" >
        <BitField size="2" start="0" name="MAM_mode_control" />
      </Register>
      <Register size="0x1" start="0xE01FC004" name="MAMTIM" >
        <BitField size="3" start="0" name="MAM_Fetch_Cycle_timing" />
      </Register>
      <Register size="0x1" start="0xE01FC040" name="MEMMAP" >
        <BitField size="2" start="0" name="MAP1_0" />
      </Register>
      <Register size="0x1" start="0xE01FC080" name="PLLCON" >
        <BitField size="1" start="0" name="PLLE" />
        <BitField size="1" start="1" name="PLLC" />
      </Register>
      <Register size="0x1" start="0xE01FC084" name="PLLCFG" >
        <BitField size="4" start="0" name="MSEL4_0" />
        <BitField size="2" start="5" name="PSEL1_0" />
      </Register>
      <Register size="0x2" start="0xE01FC088" name="PLLSTAT" >
        <BitField size="4" start="0" name="MSEL4_0" />
        <BitField size="2" start="5" name="PSEL1_0" />
        <BitField size="1" start="8" name="PLLE" />
        <BitField size="1" start="9" name="PLLC" />
        <BitField size="1" start="10" name="PLOCK" />
      </Register>
      <Register size="0x1" start="0xE01FC08C" name="PLLFEED" />
      <Register size="0x1" start="0xE01FC0C0" name="PCON" >
        <BitField size="1" start="0" name="IDL" />
        <BitField size="1" start="1" name="PD" />
      </Register>
      <Register size="0x4" start="0xE01FC0C4" name="PCONP" >
        <BitField size="1" start="1" name="PCTIM0" />
        <BitField size="1" start="2" name="PCTIM1" />
        <BitField size="1" start="3" name="PCURT0" />
        <BitField size="1" start="4" name="PCURT1" />
        <BitField size="1" start="5" name="PCPWM0" />
        <BitField size="1" start="7" name="PCI2C" />
        <BitField size="1" start="8" name="PCSPIO" />
        <BitField size="1" start="9" name="PCRTC" />
        <BitField size="1" start="10" name="PCSPI1" />
        <BitField size="1" start="12" name="PCAD" />
      </Register>
      <Register size="0x1" start="0xE01FC100" name="VPBDIV" >
        <BitField size="2" start="0" name="VPBDIV" />
        <BitField size="2" start="4" name="XCLKDIV" />
      </Register>
      <Register size="0x1" start="0xE01FC140" name="EXTINT" >
        <BitField size="1" start="0" name="EINT0" />
        <BitField size="1" start="1" name="EINT1" />
        <BitField size="1" start="2" name="EINT2" />
        <BitField size="1" start="3" name="EINT3" />
      </Register>
      <Register size="0x1" start="0xE01FC144" name="INTWAKE" />
      <Register size="0x1" start="0xE01FC148" name="EXTMODE" />
      <Register size="0x1" start="0xE01FC14C" name="EXTPOLAR" />
      <Register size="0x1" start="0xE01FC180" name="RSID" />
      <Register size="0x1" start="0xE01FC180" name="CSPR" />
    </RegisterGroup>
    <RegisterGroup start="0xFFFFF000" name="Vectored Interrupt Controller Registers" >
      <Register size="0x4" start="0xFFFFF000" name="VICIRQStatus" />
      <Register size="0x4" start="0xFFFFF004" name="VICFIQStatus" />
      <Register size="0x4" start="0xFFFFF008" name="VICRawIntr" />
      <Register size="0x4" start="0xFFFFF00C" name="VICIntSelect" />
      <Register size="0x4" start="0xFFFFF010" name="VICIntEnable" />
      <Register size="0x4" start="0xFFFFF014" name="VICIntEnClr" />
      <Register size="0x4" start="0xFFFFF018" name="VICSoftInt" />
      <Register size="0x4" start="0xFFFFF01C" name="VICSoftIntClear" />
      <Register size="0x4" start="0xFFFFF020" name="VICProtection" />
      <Register size="0x4" start="0xFFFFF030" name="VICVectAddr" />
      <Register size="0x4" start="0xFFFFF034" name="VICDefVectAddr" />
      <Register size="0x4" start="0xFFFFF100" name="VICVectAddr0" />
      <Register size="0x4" start="0xFFFFF104" name="VICVectAddr1" />
      <Register size="0x4" start="0xFFFFF108" name="VICVectAddr2" />
      <Register size="0x4" start="0xFFFFF10C" name="VICVectAddr3" />
      <Register size="0x4" start="0xFFFFF110" name="VICVectAddr4" />
      <Register size="0x4" start="0xFFFFF114" name="VICVectAddr5" />
      <Register size="0x4" start="0xFFFFF118" name="VICVectAddr6" />
      <Register size="0x4" start="0xFFFFF11C" name="VICVectAddr7" />
      <Register size="0x4" start="0xFFFFF120" name="VICVectAddr8" />
      <Register size="0x4" start="0xFFFFF124" name="VICVectAddr9" />
      <Register size="0x4" start="0xFFFFF128" name="VICVectAddr10" />
      <Register size="0x4" start="0xFFFFF12C" name="VICVectAddr11" />
      <Register size="0x4" start="0xFFFFF130" name="VICVectAddr12" />
      <Register size="0x4" start="0xFFFFF134" name="VICVectAddr13" />
      <Register size="0x4" start="0xFFFFF138" name="VICVectAddr14" />
      <Register size="0x4" start="0xFFFFF13C" name="VICVectAddr15" />
      <Register size="0x4" start="0xFFFFF200" name="VICVectCntl0" />
      <Register size="0x4" start="0xFFFFF204" name="VICVectCntl1" />
      <Register size="0x4" start="0xFFFFF208" name="VICVectCntl2" />
      <Register size="0x4" start="0xFFFFF20C" name="VICVectCntl3" />
      <Register size="0x4" start="0xFFFFF210" name="VICVectCntl4" />
      <Register size="0x4" start="0xFFFFF214" name="VICVectCntl5" />
      <Register size="0x4" start="0xFFFFF218" name="VICVectCntl6" />
      <Register size="0x4" start="0xFFFFF21C" name="VICVectCntl7" />
      <Register size="0x4" start="0xFFFFF220" name="VICVectCntl8" />
      <Register size="0x4" start="0xFFFFF224" name="VICVectCntl9" />
      <Register size="0x4" start="0xFFFFF228" name="VICVectCntl10" />
      <Register size="0x4" start="0xFFFFF22C" name="VICVectCntl11" />
      <Register size="0x4" start="0xFFFFF230" name="VICVectCntl12" />
      <Register size="0x4" start="0xFFFFF234" name="VICVectCntl13" />
      <Register size="0x4" start="0xFFFFF238" name="VICVectCntl14" />
      <Register size="0x4" start="0xFFFFF23C" name="VICVectCntl15" />
    </RegisterGroup>
  </MemorySegment>
</Root>
